halftone_converter-2.6.9.dist-info/licenses/LICENSE
halftonecv/__init__.py
halftonecv/__main__.py
halftonecv/cli.py
halftonecv/modules/__init__.py
halftonecv/modules/args.py
halftonecv/modules/color.py
halftonecv/modules/core.py
halftonecv/modules/utils.py
halftonecv/profiles/SWOP.icc
halftonecv/profiles/sGray.icc
halftonecv/profiles/sRGB.icc
halftonecv/pyinstaller/hook-halftonecv.py
halftone_converter-2.6.9.dist-info/METADATA
halftone_converter-2.6.9.dist-info/WHEEL
halftone_converter-2.6.9.dist-info/entry_points.txt
halftone_converter-2.6.9.dist-info/top_level.txt
halftone_converter-2.6.9.dist-info/RECORD
