Metadata-Version: 2.4
Name: halftone-converter
Version: 2.6.9
Summary: An image converter to create high quality halftone images
Maintainer-email: curegit <contact@curegit.jp>
License-Expression: AGPL-3.0-or-later
Project-URL: homepage, https://github.com/curegit/halftone-converter
Project-URL: repository, https://github.com/curegit/halftone-converter.git
Keywords: image processing,halftone,cmyk colors,cairo
Classifier: Programming Language :: Python :: 3 :: Only
Classifier: Topic :: Multimedia :: Graphics :: Graphics Conversion
Requires-Python: >=3.9
License-File: LICENSE
Requires-Dist: numpy>=1.24.0
Requires-Dist: pillow>=9.3.0
Requires-Dist: pycairo>=1.23.0
Requires-Dist: rich>=13.0.0
Provides-Extra: dev
Requires-Dist: pip; extra == "dev"
Requires-Dist: build; extra == "dev"
Requires-Dist: twine; extra == "dev"
Dynamic: license-file
